cell_execution_status/__init__.py
cell_execution_status/static/README.md
cell_execution_status/static/cell_execution_status.yaml
cell_execution_status/static/cell_status.png
cell_execution_status/static/index.js
cell_execution_status/static/main.css
nb_cell_execution_status-0.0.6.data/data/etc/jupyter/nbconfig/notebook.d/cell_execution_status.json
nb_cell_execution_status-0.0.6.data/data/share/jupyter/nbextensions/cell_execution_status/README.md
nb_cell_execution_status-0.0.6.data/data/share/jupyter/nbextensions/cell_execution_status/cell_execution_status.yaml
nb_cell_execution_status-0.0.6.data/data/share/jupyter/nbextensions/cell_execution_status/cell_status.png
nb_cell_execution_status-0.0.6.data/data/share/jupyter/nbextensions/cell_execution_status/index.js
nb_cell_execution_status-0.0.6.data/data/share/jupyter/nbextensions/cell_execution_status/main.css
nb_cell_execution_status-0.0.6.dist-info/LICENSE
nb_cell_execution_status-0.0.6.dist-info/METADATA
nb_cell_execution_status-0.0.6.dist-info/WHEEL
nb_cell_execution_status-0.0.6.dist-info/top_level.txt
nb_cell_execution_status-0.0.6.dist-info/RECORD
