Metadata-Version: 2.1
Name: nb-cell-execution-status
Version: 0.0.6
Summary: Classic Jupyter notebook cell execution status
Home-page: https://github.com/innovationOUtside/nb_cell_execution_status
Author: Tony Hirst
Author-email: tony.hirst@open.ac.uk
License-File: LICENSE
Requires-Dist: jupyter-nbextensions-configurator
